defusedxml/ElementTree.py
defusedxml/__init__.py
defusedxml/cElementTree.py
defusedxml/common.py
defusedxml/expatbuilder.py
defusedxml/expatreader.py
defusedxml/lxml.py
defusedxml/minidom.py
defusedxml/pulldom.py
defusedxml/sax.py
defusedxml/xmlrpc.py
defusedxml-0.8.0rc1.dist-info/LICENSE
defusedxml-0.8.0rc1.dist-info/METADATA
defusedxml-0.8.0rc1.dist-info/WHEEL
defusedxml-0.8.0rc1.dist-info/top_level.txt
defusedxml-0.8.0rc1.dist-info/RECORD
