Metadata-Version: 2.1
Name: defusedxml
Version: 0.8.0rc1
Summary: XML bomb protection for Python stdlib modules
Home-page: https://github.com/tiran/defusedxml
Download-URL: https://pypi.python.org/pypi/defusedxml
Author: Christian Heimes
Author-email: christian@python.org
Maintainer: Christian Heimes
Maintainer-email: christian@python.org
License: PSFL
Keywords: xml bomb DoS
Platform: all
Classifier: Development Status :: 6 - Mature
Classifier: Intended Audience :: Developers
Classifier: License :: OSI Approved :: Python Software Foundation License
Classifier: Natural Language :: English
Classifier: Programming Language :: Python
Classifier: Programming Language :: Python :: 3
Classifier: Programming Language :: Python :: 3.6
Classifier: Programming Language :: Python :: 3.7
Classifier: Programming Language :: Python :: 3.8
Classifier: Programming Language :: Python :: 3.9
Classifier: Programming Language :: Python :: 3.10
Classifier: Programming Language :: Python :: 3.11
Classifier: Programming Language :: Python :: 3.12
Classifier: Topic :: Text Processing :: Markup :: XML
Requires-Python: >=3.6
License-File: LICENSE
